gaia/__init__.py
gaia/api.py
gaia/cli.py
gaia/test.py
gaia_browser-0.3.5.dist-info/LICENSE
gaia_browser-0.3.5.dist-info/METADATA
gaia_browser-0.3.5.dist-info/WHEEL
gaia_browser-0.3.5.dist-info/entry_points.txt
gaia_browser-0.3.5.dist-info/top_level.txt
gaia_browser-0.3.5.dist-info/RECORD
