Metadata-Version: 2.1
Name: gaia-browser
Version: 0.3.5
Summary: the terminal-living library genesis browser
Home-page: https://github.com/fwyr/gaia
Author: Ma Weiyi
Author-email: fwyr@proton.me
License: MIT
Classifier: Programming Language :: Python :: 3
Classifier: License :: OSI Approved :: MIT License
Classifier: Operating System :: OS Independent
Requires-Python: >=3.8
License-File: LICENSE
Requires-Dist: requests
Requires-Dist: rich
Requires-Dist: beautifulsoup4
Requires-Dist: pyfiglet
Requires-Dist: libgen-api
Requires-Dist: fake-useragent
